scrapedia/VERSION
scrapedia/__init__.py
scrapedia/errors.py
scrapedia/models.py
scrapedia/packers.py
scrapedia/parsers.py
scrapedia/pipeline.py
scrapedia/requesters.py
scrapedia/scrapers.py
scrapedia/seekers.py
scrapedia/version.py
scrapedia-0.1.0.dist-info/LICENSE
scrapedia-0.1.0.dist-info/METADATA
scrapedia-0.1.0.dist-info/WHEEL
scrapedia-0.1.0.dist-info/top_level.txt
scrapedia-0.1.0.dist-info/RECORD
