Metadata-Version: 2.1
Name: scrapedia
Version: 0.1.0
Summary: A scraper used for the extraction of brazilizan soccer historic data from the webpage futpedia.globo.com
Home-page: https://github.com/LucasRGoes/scrapedia
Author: Lucas Góes
Author-email: lucas.rd.goes@gmail.com
License: MIT License
Requires-Dist: beautifulsoup4 (==4.7.1)
Requires-Dist: cachetools (==3.1.1)
Requires-Dist: pandas (==0.24.2)
Requires-Dist: requests (==2.22.0)
Requires-Dist: Unidecode (==1.1.1)
